terapp/__init__.py
terapp/app/__init__.py
terapp/app/app.py
terapp/app/config.py
terapp/app/context.py
terapp/app/errors.py
terapp/app/interfaces.py
terapp/extension/__init__.py
terapp/extension/state.py
terapp/extension/support.py
terapp/ui/__init__.py
terapp/ui/common.py
terapp/ui/header.py
terapp/ui/interfaces.py
terapp-0.1.0.dist-info/LICENSE
terapp-0.1.0.dist-info/METADATA
terapp-0.1.0.dist-info/WHEEL
terapp-0.1.0.dist-info/top_level.txt
terapp-0.1.0.dist-info/RECORD
