Metadata-Version: 2.1
Name: terapp
Version: 0.1.0
Summary: Ter is a simple CLI framework for Python App
Home-page: https://github.com/Ming-doan/ter
Author: Ming-doan
Author-email: quangminh57dng@gmail.com
License: MIT
Classifier: License :: OSI Approved :: MIT License
Classifier: Programming Language :: Python :: 3.10
Classifier: Operating System :: OS Independent
Requires-Python: >=3.10
License-File: LICENSE
